{
  "data": [
    {
      "id": 1,
      "name": "App Repository",
      "owner": {
        "login": "LinekerValim",
        "avatar_url": "https://avatars.githubusercontent.com/u/81521229?s=400&u=422b53bf90ee69e1673febfe8c5daab2072580b5&v=4"
      },
      "stargazers_count": 0,
      "language": "Kotlin",
      "html_url": "https://github.com/lineker1/FilmeFlix",
      "description": "App simulando NetFlix"
    },
    {
       "id": 2,
      "name": "App Repository",
      "owner": {
        "login": "LinekerValim",
        "avatar_url": "https://avatars.githubusercontent.com/u/81521229?s=400&u=422b53bf90ee69e1673febfe8c5daab2072580b5&v=4"
      },
      "stargazers_count": 0,
      "language": "Kotlin",
      "html_url": "https://github.com/lineker1/Soccer_News",
      "description": "App de noticías sobre o futebol feminino."
    },
    {
       "id": 3,
      "name": "App Repository",
      "owner": {
        "login": "LinekerValim",
        "avatar_url": "https://avatars.githubusercontent.com/u/81521229?s=400&u=422b53bf90ee69e1673febfe8c5daab2072580b5&v=4"
      },
      "stargazers_count": 0,
      "language": "Kotlin",
      "html_url": "https://github.com/lineker1/Matchs-Simulator",
      "description": "App simulador de partidas."
    },
    {
       "id": 4,
      "name": "App Repository",
      "owner": {
        "login": "LinekerValim",
        "avatar_url": "https://avatars.githubusercontent.com/u/81521229?s=400&u=422b53bf90ee69e1673febfe8c5daab2072580b5&v=4"
      },
      "stargazers_count": 0,
      "language": "Kotlin",
      "html_url": "https://github.com/lineker1/CryptoApp",
      "description": "App com listagem de crypto moedas."
    }
  ]
}
